{"id":"dropdown;goes-back-to-showing-the-placeholder-when-all-the-selected-options-get-deselected;chromium;linux-6-11-0-1018-azure;chromium-143-0-7499-4;firefox;firefox-144-0-2;webkit;webkit-26-0","name":"goes back to showing the placeholder when all the selected options get deselected","title":"goes back to showing the placeholder when all the selected options get deselected - webkit","manual":false,"testSteps":[{"number":1,"description":"goes back to showing the placeholder when all the selected options get deselected #1 - Retries: Attempt #1","startTime":"2026-01-05T21:10:28.654Z","children":[{"number":2,"description":"Tess selects [ &apos;First&apos;, &apos;Second&apos; ] from dropdown","startTime":"2026-01-05T21:10:28.746Z","children":[{"number":3,"description":"Tess iterates over [ &apos;First&apos;, &apos;Second&apos; ]","startTime":"2026-01-05T21:10:28.746Z","children":[{"number":4,"description":"Tess selects &apos;First&apos; from dropdown","startTime":"2026-01-05T21:10:28.757Z","children":[{"number":5,"description":"Tess opens the dropdown","startTime":"2026-01-05T21:10:28.757Z","children":[{"number":6,"description":"Tess checks whether CSS classes of dropdown does not contain &quot;dropdown-expanded&quot;","startTime":"2026-01-05T21:10:28.758Z","children":[{"number":7,"description":"Tess clicks on input field","startTime":"2026-01-05T21:10:28.772Z","children":[],"reportData":[],"screenshots":[{"screenshot":"photo-linux-chromium-143.0.7499.4-tess-clicks-on-input-field-2f22142773.png","screenshotName":"photo-linux-chromium-143.0.7499.4-tess-clicks-on-input-field-2f22142773.png","timeStamp":1767647428909},{"screenshot":"photo-linux-chromium-143.0.7499.4-tess-clicks-on-input-field-1a84a27975.png","screenshotName":"photo-linux-chromium-143.0.7499.4-tess-clicks-on-input-field-1a84a27975.png","timeStamp":1767647428975},{"screenshot":"photo-linux-chromium-143.0.7499.4-tess-clicks-on-input-field-187bd07516.png","screenshotName":"photo-linux-chromium-143.0.7499.4-tess-clicks-on-input-field-187bd07516.png","timeStamp":1767647429042},{"screenshot":"photo-linux-chromium-143.0.7499.4-tess-clicks-on-input-field-bc166f23ca.png","screenshotName":"photo-linux-chromium-143.0.7499.4-tess-clicks-on-input-field-bc166f23ca.png","timeStamp":1767647429009},{"screenshot":"photo-linux-chromium-143.0.7499.4-tess-clicks-on-input-field-c54fee5bc0.png","screenshotName":"photo-linux-chromium-143.0.7499.4-tess-clicks-on-input-field-c54fee5bc0.png","timeStamp":1767647428876},{"screenshot":"photo-linux-chromium-143.0.7499.4-tess-clicks-on-input-field-24daf41c53.png","screenshotName":"photo-linux-chromium-143.0.7499.4-tess-clicks-on-input-field-24daf41c53.png","timeStamp":1767647428942}],"duration":73,"result":"SUCCESS"},{"number":8,"description":"Tess waits until page element located by css (&apos;.dropdown-available-options&apos;) does become visible","startTime":"2026-01-05T21:10:29.052Z","children":[],"reportData":[],"screenshots":[{"screenshot":"photo-linux-chromium-143.0.7499.4-tess-waits-until-page-element-locate-2d9c5fdee4.png","screenshotName":"photo-linux-chromium-143.0.7499.4-tess-waits-until-page-element-locate-2d9c5fdee4.png","timeStamp":1767647429109},{"screenshot":"photo-linux-chromium-143.0.7499.4-tess-waits-until-page-element-locate-0f502f1c30.png","screenshotName":"photo-linux-chromium-143.0.7499.4-tess-waits-until-page-element-locate-0f502f1c30.png","timeStamp":1767647429142},{"screenshot":"photo-linux-chromium-143.0.7499.4-tess-waits-until-page-element-locate-0193e2fd9e.png","screenshotName":"photo-linux-chromium-143.0.7499.4-tess-waits-until-page-element-locate-0193e2fd9e.png","timeStamp":1767647429176},{"screenshot":"photo-linux-chromium-143.0.7499.4-tess-waits-until-page-element-locate-9991c72bd0.png","screenshotName":"photo-linux-chromium-143.0.7499.4-tess-waits-until-page-element-locate-9991c72bd0.png","timeStamp":1767647429277},{"screenshot":"photo-linux-chromium-143.0.7499.4-tess-waits-until-page-element-locate-1b7a78406c.png","screenshotName":"photo-linux-chromium-143.0.7499.4-tess-waits-until-page-element-locate-1b7a78406c.png","timeStamp":1767647429242},{"screenshot":"photo-linux-chromium-143.0.7499.4-tess-waits-until-page-element-locate-c2b42103ec.png","screenshotName":"photo-linux-chromium-143.0.7499.4-tess-waits-until-page-element-locate-c2b42103ec.png","timeStamp":1767647429210}],"duration":25,"result":"SUCCESS"}],"reportData":[],"screenshots":[],"duration":522,"result":"SUCCESS"}],"reportData":[],"screenshots":[],"duration":534,"result":"SUCCESS"},{"number":9,"description":"Tess clicks on the first of page elements located by css (&apos;.dropdown-available-option&apos;) of page element located by css (&apos;.dropdown-available-options&apos;) where Text does include &quot;First&quot;","startTime":"2026-01-05T21:10:29.302Z","children":[],"reportData":[],"screenshots":[{"screenshot":"photo-linux-chromium-143.0.7499.4-tess-clicks-on-the-first-of-page-ele-4eaf4c814f.png","screenshotName":"photo-linux-chromium-143.0.7499.4-tess-clicks-on-the-first-of-page-ele-4eaf4c814f.png","timeStamp":1767647429409},{"screenshot":"photo-linux-chromium-143.0.7499.4-tess-clicks-on-the-first-of-page-ele-f21fc2ec6d.png","screenshotName":"photo-linux-chromium-143.0.7499.4-tess-clicks-on-the-first-of-page-ele-f21fc2ec6d.png","timeStamp":1767647429443},{"screenshot":"photo-linux-chromium-143.0.7499.4-tess-clicks-on-the-first-of-page-ele-693c4ab60b.png","screenshotName":"photo-linux-chromium-143.0.7499.4-tess-clicks-on-the-first-of-page-ele-693c4ab60b.png","timeStamp":1767647429476},{"screenshot":"photo-linux-chromium-143.0.7499.4-tess-clicks-on-the-first-of-page-ele-bc215218c1.png","screenshotName":"photo-linux-chromium-143.0.7499.4-tess-clicks-on-the-first-of-page-ele-bc215218c1.png","timeStamp":1767647429508},{"screenshot":"photo-linux-chromium-143.0.7499.4-tess-clicks-on-the-first-of-page-ele-503a1b12a5.png","screenshotName":"photo-linux-chromium-143.0.7499.4-tess-clicks-on-the-first-of-page-ele-503a1b12a5.png","timeStamp":1767647429542},{"screenshot":"photo-linux-chromium-143.0.7499.4-tess-clicks-on-the-first-of-page-ele-1d34061274.png","screenshotName":"photo-linux-chromium-143.0.7499.4-tess-clicks-on-the-first-of-page-ele-1d34061274.png","timeStamp":1767647429575}],"duration":77,"result":"SUCCESS"},{"number":10,"description":"Tess ensures that the text of page elements located by css (&apos;.dropdown-selected-option&apos;) of input field does contain at least one item that does start with &quot;First&quot;","startTime":"2026-01-05T21:10:29.583Z","children":[],"reportData":[],"screenshots":[{"screenshot":"photo-linux-chromium-143.0.7499.4-tess-ensures-that-the-text-of-page-e-5f06b34e0a.png","screenshotName":"photo-linux-chromium-143.0.7499.4-tess-ensures-that-the-text-of-page-e-5f06b34e0a.png","timeStamp":1767647429625},{"screenshot":"photo-linux-chromium-143.0.7499.4-tess-ensures-that-the-text-of-page-e-ba42cf8db6.png","screenshotName":"photo-linux-chromium-143.0.7499.4-tess-ensures-that-the-text-of-page-e-ba42cf8db6.png","timeStamp":1767647429658},{"screenshot":"photo-linux-chromium-143.0.7499.4-tess-ensures-that-the-text-of-page-e-44b6ab91e9.png","screenshotName":"photo-linux-chromium-143.0.7499.4-tess-ensures-that-the-text-of-page-e-44b6ab91e9.png","timeStamp":1767647429691},{"screenshot":"photo-linux-chromium-143.0.7499.4-tess-ensures-that-the-text-of-page-e-9f10285049.png","screenshotName":"photo-linux-chromium-143.0.7499.4-tess-ensures-that-the-text-of-page-e-9f10285049.png","timeStamp":1767647429725},{"screenshot":"photo-linux-chromium-143.0.7499.4-tess-ensures-that-the-text-of-page-e-90e3fa89b1.png","screenshotName":"photo-linux-chromium-143.0.7499.4-tess-ensures-that-the-text-of-page-e-90e3fa89b1.png","timeStamp":1767647429758},{"screenshot":"photo-linux-chromium-143.0.7499.4-tess-ensures-that-the-text-of-page-e-bb423f6ad2.png","screenshotName":"photo-linux-chromium-143.0.7499.4-tess-ensures-that-the-text-of-page-e-bb423f6ad2.png","timeStamp":1767647429791}],"duration":7,"result":"SUCCESS"}],"reportData":[],"screenshots":[],"duration":1037,"result":"SUCCESS"},{"number":11,"description":"Tess selects &apos;Second&apos; from dropdown","startTime":"2026-01-05T21:10:29.823Z","children":[{"number":12,"description":"Tess opens the dropdown","startTime":"2026-01-05T21:10:29.823Z","children":[{"number":13,"description":"Tess checks whether CSS classes of dropdown does not contain &quot;dropdown-expanded&quot;","startTime":"2026-01-05T21:10:29.824Z","children":[{"number":14,"description":"Tess clicks on input field","startTime":"2026-01-05T21:10:29.828Z","children":[],"reportData":[],"screenshots":[{"screenshot":"photo-linux-chromium-143.0.7499.4-tess-clicks-on-input-field-84eabf136a.png","screenshotName":"photo-linux-chromium-143.0.7499.4-tess-clicks-on-input-field-84eabf136a.png","timeStamp":1767647429926},{"screenshot":"photo-linux-chromium-143.0.7499.4-tess-clicks-on-input-field-2f029bb505.png","screenshotName":"photo-linux-chromium-143.0.7499.4-tess-clicks-on-input-field-2f029bb505.png","timeStamp":1767647429958},{"screenshot":"photo-linux-chromium-143.0.7499.4-tess-clicks-on-input-field-2b855559c4.png","screenshotName":"photo-linux-chromium-143.0.7499.4-tess-clicks-on-input-field-2b855559c4.png","timeStamp":1767647429992},{"screenshot":"photo-linux-chromium-143.0.7499.4-tess-clicks-on-input-field-164eb1efb5.png","screenshotName":"photo-linux-chromium-143.0.7499.4-tess-clicks-on-input-field-164eb1efb5.png","timeStamp":1767647430025},{"screenshot":"photo-linux-chromium-143.0.7499.4-tess-clicks-on-input-field-70c473af73.png","screenshotName":"photo-linux-chromium-143.0.7499.4-tess-clicks-on-input-field-70c473af73.png","timeStamp":1767647430059},{"screenshot":"photo-linux-chromium-143.0.7499.4-tess-clicks-on-input-field-25677e72e6.png","screenshotName":"photo-linux-chromium-143.0.7499.4-tess-clicks-on-input-field-25677e72e6.png","timeStamp":1767647430092}],"duration":66,"result":"SUCCESS"},{"number":15,"description":"Tess waits until page element located by css (&apos;.dropdown-available-options&apos;) does become visible","startTime":"2026-01-05T21:10:30.098Z","children":[],"reportData":[],"screenshots":[{"screenshot":"photo-linux-chromium-143.0.7499.4-tess-waits-until-page-element-locate-642b6a85ce.png","screenshotName":"photo-linux-chromium-143.0.7499.4-tess-waits-until-page-element-locate-642b6a85ce.png","timeStamp":1767647430158},{"screenshot":"photo-linux-chromium-143.0.7499.4-tess-waits-until-page-element-locate-948183d387.png","screenshotName":"photo-linux-chromium-143.0.7499.4-tess-waits-until-page-element-locate-948183d387.png","timeStamp":1767647430192},{"screenshot":"photo-linux-chromium-143.0.7499.4-tess-waits-until-page-element-locate-d5bf591eae.png","screenshotName":"photo-linux-chromium-143.0.7499.4-tess-waits-until-page-element-locate-d5bf591eae.png","timeStamp":1767647430259},{"screenshot":"photo-linux-chromium-143.0.7499.4-tess-waits-until-page-element-locate-02209fcdbb.png","screenshotName":"photo-linux-chromium-143.0.7499.4-tess-waits-until-page-element-locate-02209fcdbb.png","timeStamp":1767647430226},{"screenshot":"photo-linux-chromium-143.0.7499.4-tess-waits-until-page-element-locate-3709b6dbd1.png","screenshotName":"photo-linux-chromium-143.0.7499.4-tess-waits-until-page-element-locate-3709b6dbd1.png","timeStamp":1767647430292},{"screenshot":"photo-linux-chromium-143.0.7499.4-tess-waits-until-page-element-locate-8e6421e0f0.png","screenshotName":"photo-linux-chromium-143.0.7499.4-tess-waits-until-page-element-locate-8e6421e0f0.png","timeStamp":1767647430326}],"duration":27,"result":"SUCCESS"}],"reportData":[],"screenshots":[],"duration":504,"result":"SUCCESS"}],"reportData":[],"screenshots":[],"duration":515,"result":"SUCCESS"},{"number":16,"description":"Tess clicks on the first of page elements located by css (&apos;.dropdown-available-option&apos;) of page element located by css (&apos;.dropdown-available-options&apos;) where Text does include &quot;Second&quot;","startTime":"2026-01-05T21:10:30.349Z","children":[],"reportData":[],"screenshots":[{"screenshot":"photo-linux-chromium-143.0.7499.4-tess-clicks-on-the-first-of-page-ele-fba155a246.png","screenshotName":"photo-linux-chromium-143.0.7499.4-tess-clicks-on-the-first-of-page-ele-fba155a246.png","timeStamp":1767647430459},{"screenshot":"photo-linux-chromium-143.0.7499.4-tess-clicks-on-the-first-of-page-ele-984fc6b3e6.png","screenshotName":"photo-linux-chromium-143.0.7499.4-tess-clicks-on-the-first-of-page-ele-984fc6b3e6.png","timeStamp":1767647430493},{"screenshot":"photo-linux-chromium-143.0.7499.4-tess-clicks-on-the-first-of-page-ele-b0c1260f75.png","screenshotName":"photo-linux-chromium-143.0.7499.4-tess-clicks-on-the-first-of-page-ele-b0c1260f75.png","timeStamp":1767647430526},{"screenshot":"photo-linux-chromium-143.0.7499.4-tess-clicks-on-the-first-of-page-ele-c28701f1be.png","screenshotName":"photo-linux-chromium-143.0.7499.4-tess-clicks-on-the-first-of-page-ele-c28701f1be.png","timeStamp":1767647430559},{"screenshot":"photo-linux-chromium-143.0.7499.4-tess-clicks-on-the-first-of-page-ele-5d8c4068ab.png","screenshotName":"photo-linux-chromium-143.0.7499.4-tess-clicks-on-the-first-of-page-ele-5d8c4068ab.png","timeStamp":1767647430592},{"screenshot":"photo-linux-chromium-143.0.7499.4-tess-clicks-on-the-first-of-page-ele-af8d3cda58.png","screenshotName":"photo-linux-chromium-143.0.7499.4-tess-clicks-on-the-first-of-page-ele-af8d3cda58.png","timeStamp":1767647430625}],"duration":78,"result":"SUCCESS"},{"number":17,"description":"Tess ensures that the text of page elements located by css (&apos;.dropdown-selected-option&apos;) of input field does contain at least one item that does start with &quot;Second&quot;","startTime":"2026-01-05T21:10:30.632Z","children":[],"reportData":[],"screenshots":[{"screenshot":"photo-linux-chromium-143.0.7499.4-tess-ensures-that-the-text-of-page-e-e9ecc7e3c1.png","screenshotName":"photo-linux-chromium-143.0.7499.4-tess-ensures-that-the-text-of-page-e-e9ecc7e3c1.png","timeStamp":1767647430708},{"screenshot":"photo-linux-chromium-143.0.7499.4-tess-ensures-that-the-text-of-page-e-504620dfa8.png","screenshotName":"photo-linux-chromium-143.0.7499.4-tess-ensures-that-the-text-of-page-e-504620dfa8.png","timeStamp":1767647430675},{"screenshot":"photo-linux-chromium-143.0.7499.4-tess-ensures-that-the-text-of-page-e-a7db08ff44.png","screenshotName":"photo-linux-chromium-143.0.7499.4-tess-ensures-that-the-text-of-page-e-a7db08ff44.png","timeStamp":1767647430742},{"screenshot":"photo-linux-chromium-143.0.7499.4-tess-ensures-that-the-text-of-page-e-732a20811e.png","screenshotName":"photo-linux-chromium-143.0.7499.4-tess-ensures-that-the-text-of-page-e-732a20811e.png","timeStamp":1767647430775},{"screenshot":"photo-linux-chromium-143.0.7499.4-tess-ensures-that-the-text-of-page-e-b1006dd456.png","screenshotName":"photo-linux-chromium-143.0.7499.4-tess-ensures-that-the-text-of-page-e-b1006dd456.png","timeStamp":1767647430808},{"screenshot":"photo-linux-chromium-143.0.7499.4-tess-ensures-that-the-text-of-page-e-371022736a.png","screenshotName":"photo-linux-chromium-143.0.7499.4-tess-ensures-that-the-text-of-page-e-371022736a.png","timeStamp":1767647430843}],"duration":10,"result":"SUCCESS"}],"reportData":[],"screenshots":[],"duration":1022,"result":"SUCCESS"}],"reportData":[],"screenshots":[],"duration":2109,"result":"SUCCESS"}],"reportData":[],"screenshots":[],"duration":2119,"result":"SUCCESS"},{"number":18,"description":"Tess deselects [ &apos;First&apos;, &apos;Second&apos; ] from dropdown","startTime":"2026-01-05T21:10:30.876Z","children":[{"number":19,"description":"Tess iterates over [ &apos;First&apos;, &apos;Second&apos; ]","startTime":"2026-01-05T21:10:30.876Z","children":[{"number":20,"description":"Tess deselects &apos;First&apos; from dropdown","startTime":"2026-01-05T21:10:30.885Z","children":[{"number":21,"description":"Tess clicks on deselect button of the first of page elements located by css (&apos;.dropdown-selected-option&apos;) of input field where Text does include &quot;First&quot;","startTime":"2026-01-05T21:10:30.885Z","children":[],"reportData":[],"screenshots":[{"screenshot":"photo-linux-chromium-143.0.7499.4-tess-clicks-on-deselect-button-of-th-aa4d34fdcb.png","screenshotName":"photo-linux-chromium-143.0.7499.4-tess-clicks-on-deselect-button-of-th-aa4d34fdcb.png","timeStamp":1767647431023},{"screenshot":"photo-linux-chromium-143.0.7499.4-tess-clicks-on-deselect-button-of-th-aa4d34fdcb.png","screenshotName":"photo-linux-chromium-143.0.7499.4-tess-clicks-on-deselect-button-of-th-aa4d34fdcb.png","timeStamp":1767647431057},{"screenshot":"photo-linux-chromium-143.0.7499.4-tess-clicks-on-deselect-button-of-th-aa4d34fdcb.png","screenshotName":"photo-linux-chromium-143.0.7499.4-tess-clicks-on-deselect-button-of-th-aa4d34fdcb.png","timeStamp":1767647430992},{"screenshot":"photo-linux-chromium-143.0.7499.4-tess-clicks-on-deselect-button-of-th-aa4d34fdcb.png","screenshotName":"photo-linux-chromium-143.0.7499.4-tess-clicks-on-deselect-button-of-th-aa4d34fdcb.png","timeStamp":1767647431091},{"screenshot":"photo-linux-chromium-143.0.7499.4-tess-clicks-on-deselect-button-of-th-aa4d34fdcb.png","screenshotName":"photo-linux-chromium-143.0.7499.4-tess-clicks-on-deselect-button-of-th-aa4d34fdcb.png","timeStamp":1767647431158},{"screenshot":"photo-linux-chromium-143.0.7499.4-tess-clicks-on-deselect-button-of-th-aa4d34fdcb.png","screenshotName":"photo-linux-chromium-143.0.7499.4-tess-clicks-on-deselect-button-of-th-aa4d34fdcb.png","timeStamp":1767647431124}],"duration":76,"result":"SUCCESS"},{"number":22,"description":"Tess ensures that the text of page elements located by css (&apos;.dropdown-selected-option&apos;) of input field does not contain &quot;First&quot;","startTime":"2026-01-05T21:10:31.165Z","children":[],"reportData":[],"screenshots":[{"screenshot":"photo-linux-chromium-143.0.7499.4-tess-ensures-that-the-text-of-page-e-aa4d34fdcb.png","screenshotName":"photo-linux-chromium-143.0.7499.4-tess-ensures-that-the-text-of-page-e-aa4d34fdcb.png","timeStamp":1767647431240},{"screenshot":"photo-linux-chromium-143.0.7499.4-tess-ensures-that-the-text-of-page-e-aa4d34fdcb.png","screenshotName":"photo-linux-chromium-143.0.7499.4-tess-ensures-that-the-text-of-page-e-aa4d34fdcb.png","timeStamp":1767647431274},{"screenshot":"photo-linux-chromium-143.0.7499.4-tess-ensures-that-the-text-of-page-e-aa4d34fdcb.png","screenshotName":"photo-linux-chromium-143.0.7499.4-tess-ensures-that-the-text-of-page-e-aa4d34fdcb.png","timeStamp":1767647431208},{"screenshot":"photo-linux-chromium-143.0.7499.4-tess-ensures-that-the-text-of-page-e-aa4d34fdcb.png","screenshotName":"photo-linux-chromium-143.0.7499.4-tess-ensures-that-the-text-of-page-e-aa4d34fdcb.png","timeStamp":1767647431309},{"screenshot":"photo-linux-chromium-143.0.7499.4-tess-ensures-that-the-text-of-page-e-aa4d34fdcb.png","screenshotName":"photo-linux-chromium-143.0.7499.4-tess-ensures-that-the-text-of-page-e-aa4d34fdcb.png","timeStamp":1767647431340},{"screenshot":"photo-linux-chromium-143.0.7499.4-tess-ensures-that-the-text-of-page-e-aa4d34fdcb.png","screenshotName":"photo-linux-chromium-143.0.7499.4-tess-ensures-that-the-text-of-page-e-aa4d34fdcb.png","timeStamp":1767647431375}],"duration":7,"result":"SUCCESS"}],"reportData":[],"screenshots":[],"duration":492,"result":"SUCCESS"},{"number":23,"description":"Tess deselects &apos;Second&apos; from dropdown","startTime":"2026-01-05T21:10:31.401Z","children":[{"number":24,"description":"Tess clicks on deselect button of the first of page elements located by css (&apos;.dropdown-selected-option&apos;) of input field where Text does include &quot;Second&quot;","startTime":"2026-01-05T21:10:31.402Z","children":[],"reportData":[],"screenshots":[{"screenshot":"photo-linux-chromium-143.0.7499.4-tess-clicks-on-deselect-button-of-th-070dbeac15.png","screenshotName":"photo-linux-chromium-143.0.7499.4-tess-clicks-on-deselect-button-of-th-070dbeac15.png","timeStamp":1767647431491},{"screenshot":"photo-linux-chromium-143.0.7499.4-tess-clicks-on-deselect-button-of-th-070dbeac15.png","screenshotName":"photo-linux-chromium-143.0.7499.4-tess-clicks-on-deselect-button-of-th-070dbeac15.png","timeStamp":1767647431525},{"screenshot":"photo-linux-chromium-143.0.7499.4-tess-clicks-on-deselect-button-of-th-070dbeac15.png","screenshotName":"photo-linux-chromium-143.0.7499.4-tess-clicks-on-deselect-button-of-th-070dbeac15.png","timeStamp":1767647431557},{"screenshot":"photo-linux-chromium-143.0.7499.4-tess-clicks-on-deselect-button-of-th-070dbeac15.png","screenshotName":"photo-linux-chromium-143.0.7499.4-tess-clicks-on-deselect-button-of-th-070dbeac15.png","timeStamp":1767647431592},{"screenshot":"photo-linux-chromium-143.0.7499.4-tess-clicks-on-deselect-button-of-th-070dbeac15.png","screenshotName":"photo-linux-chromium-143.0.7499.4-tess-clicks-on-deselect-button-of-th-070dbeac15.png","timeStamp":1767647431624},{"screenshot":"photo-linux-chromium-143.0.7499.4-tess-clicks-on-deselect-button-of-th-070dbeac15.png","screenshotName":"photo-linux-chromium-143.0.7499.4-tess-clicks-on-deselect-button-of-th-070dbeac15.png","timeStamp":1767647431658}],"duration":58,"result":"SUCCESS"},{"number":25,"description":"Tess ensures that the text of page elements located by css (&apos;.dropdown-selected-option&apos;) of input field does not contain &quot;Second&quot;","startTime":"2026-01-05T21:10:31.663Z","children":[],"reportData":[],"screenshots":[{"screenshot":"photo-linux-chromium-143.0.7499.4-tess-ensures-that-the-text-of-page-e-070dbeac15.png","screenshotName":"photo-linux-chromium-143.0.7499.4-tess-ensures-that-the-text-of-page-e-070dbeac15.png","timeStamp":1767647431708},{"screenshot":"photo-linux-chromium-143.0.7499.4-tess-ensures-that-the-text-of-page-e-070dbeac15.png","screenshotName":"photo-linux-chromium-143.0.7499.4-tess-ensures-that-the-text-of-page-e-070dbeac15.png","timeStamp":1767647431742},{"screenshot":"photo-linux-chromium-143.0.7499.4-tess-ensures-that-the-text-of-page-e-070dbeac15.png","screenshotName":"photo-linux-chromium-143.0.7499.4-tess-ensures-that-the-text-of-page-e-070dbeac15.png","timeStamp":1767647431775},{"screenshot":"photo-linux-chromium-143.0.7499.4-tess-ensures-that-the-text-of-page-e-070dbeac15.png","screenshotName":"photo-linux-chromium-143.0.7499.4-tess-ensures-that-the-text-of-page-e-070dbeac15.png","timeStamp":1767647431807},{"screenshot":"photo-linux-chromium-143.0.7499.4-tess-ensures-that-the-text-of-page-e-070dbeac15.png","screenshotName":"photo-linux-chromium-143.0.7499.4-tess-ensures-that-the-text-of-page-e-070dbeac15.png","timeStamp":1767647431841},{"screenshot":"photo-linux-chromium-143.0.7499.4-tess-ensures-that-the-text-of-page-e-070dbeac15.png","screenshotName":"photo-linux-chromium-143.0.7499.4-tess-ensures-that-the-text-of-page-e-070dbeac15.png","timeStamp":1767647431874}],"duration":6,"result":"SUCCESS"}],"reportData":[],"screenshots":[],"duration":482,"result":"SUCCESS"}],"reportData":[],"screenshots":[],"duration":1017,"result":"SUCCESS"}],"reportData":[],"screenshots":[],"duration":1028,"result":"SUCCESS"},{"number":26,"description":"Tess ensures that 0 does equal 0","startTime":"2026-01-05T21:10:31.918Z","children":[],"reportData":[],"screenshots":[{"screenshot":"photo-linux-chromium-143.0.7499.4-tess-ensures-that-0-does-equal-0-070dbeac15.png","screenshotName":"photo-linux-chromium-143.0.7499.4-tess-ensures-that-0-does-equal-0-070dbeac15.png","timeStamp":1767647431949},{"screenshot":"photo-linux-chromium-143.0.7499.4-tess-ensures-that-0-does-equal-0-070dbeac15.png","screenshotName":"photo-linux-chromium-143.0.7499.4-tess-ensures-that-0-does-equal-0-070dbeac15.png","timeStamp":1767647431973},{"screenshot":"photo-linux-chromium-143.0.7499.4-tess-ensures-that-0-does-equal-0-070dbeac15.png","screenshotName":"photo-linux-chromium-143.0.7499.4-tess-ensures-that-0-does-equal-0-070dbeac15.png","timeStamp":1767647432007},{"screenshot":"photo-linux-chromium-143.0.7499.4-tess-ensures-that-0-does-equal-0-070dbeac15.png","screenshotName":"photo-linux-chromium-143.0.7499.4-tess-ensures-that-0-does-equal-0-070dbeac15.png","timeStamp":1767647432040},{"screenshot":"photo-linux-chromium-143.0.7499.4-tess-ensures-that-0-does-equal-0-070dbeac15.png","screenshotName":"photo-linux-chromium-143.0.7499.4-tess-ensures-that-0-does-equal-0-070dbeac15.png","timeStamp":1767647432073},{"screenshot":"photo-linux-chromium-143.0.7499.4-tess-ensures-that-0-does-equal-0-070dbeac15.png","screenshotName":"photo-linux-chromium-143.0.7499.4-tess-ensures-that-0-does-equal-0-070dbeac15.png","timeStamp":1767647432107}],"duration":8,"result":"SUCCESS"},{"number":27,"description":"Tess ensures that placeholder of dropdown does equal &quot;Select option&quot;","startTime":"2026-01-05T21:10:32.110Z","children":[],"reportData":[],"screenshots":[{"screenshot":"photo-linux-chromium-143.0.7499.4-tess-ensures-that-placeholder-of-dro-070dbeac15.png","screenshotName":"photo-linux-chromium-143.0.7499.4-tess-ensures-that-placeholder-of-dro-070dbeac15.png","timeStamp":1767647432141},{"screenshot":"photo-linux-chromium-143.0.7499.4-tess-ensures-that-placeholder-of-dro-070dbeac15.png","screenshotName":"photo-linux-chromium-143.0.7499.4-tess-ensures-that-placeholder-of-dro-070dbeac15.png","timeStamp":1767647432174},{"screenshot":"photo-linux-chromium-143.0.7499.4-tess-ensures-that-placeholder-of-dro-070dbeac15.png","screenshotName":"photo-linux-chromium-143.0.7499.4-tess-ensures-that-placeholder-of-dro-070dbeac15.png","timeStamp":1767647432208},{"screenshot":"photo-linux-chromium-143.0.7499.4-tess-ensures-that-placeholder-of-dro-070dbeac15.png","screenshotName":"photo-linux-chromium-143.0.7499.4-tess-ensures-that-placeholder-of-dro-070dbeac15.png","timeStamp":1767647432241},{"screenshot":"photo-linux-chromium-143.0.7499.4-tess-ensures-that-placeholder-of-dro-070dbeac15.png","screenshotName":"photo-linux-chromium-143.0.7499.4-tess-ensures-that-placeholder-of-dro-070dbeac15.png","timeStamp":1767647432274},{"screenshot":"photo-linux-chromium-143.0.7499.4-tess-ensures-that-placeholder-of-dro-070dbeac15.png","screenshotName":"photo-linux-chromium-143.0.7499.4-tess-ensures-that-placeholder-of-dro-070dbeac15.png","timeStamp":1767647432308}],"duration":5,"result":"SUCCESS"}],"reportData":[],"screenshots":[],"duration":3803,"result":"SUCCESS"},{"number":28,"description":"goes back to showing the placeholder when all the selected options get deselected #2 - Retries: Attempt #1","startTime":"2026-01-05T21:10:41.770Z","children":[{"number":29,"description":"Tess selects [ &apos;First&apos;, &apos;Second&apos; ] from dropdown","startTime":"2026-01-05T21:10:41.975Z","children":[{"number":30,"description":"Tess iterates over [ &apos;First&apos;, &apos;Second&apos; ]","startTime":"2026-01-05T21:10:41.976Z","children":[{"number":31,"description":"Tess selects &apos;First&apos; from dropdown","startTime":"2026-01-05T21:10:41.988Z","children":[{"number":32,"description":"Tess opens the dropdown","startTime":"2026-01-05T21:10:41.988Z","children":[{"number":33,"description":"Tess checks whether CSS classes of dropdown does not contain &quot;dropdown-expanded&quot;","startTime":"2026-01-05T21:10:41.989Z","children":[{"number":34,"description":"Tess clicks on input field","startTime":"2026-01-05T21:10:42.018Z","children":[],"reportData":[],"screenshots":[{"screenshot":"photo-linux-firefox-144.0.2-tess-clicks-on-input-field-fc828fe961.png","screenshotName":"photo-linux-firefox-144.0.2-tess-clicks-on-input-field-fc828fe961.png","timeStamp":1767647442121},{"screenshot":"photo-linux-firefox-144.0.2-tess-clicks-on-input-field-0105d52df6.png","screenshotName":"photo-linux-firefox-144.0.2-tess-clicks-on-input-field-0105d52df6.png","timeStamp":1767647442140},{"screenshot":"photo-linux-firefox-144.0.2-tess-clicks-on-input-field-225388a537.png","screenshotName":"photo-linux-firefox-144.0.2-tess-clicks-on-input-field-225388a537.png","timeStamp":1767647442159},{"screenshot":"photo-linux-firefox-144.0.2-tess-clicks-on-input-field-b5684dfac4.png","screenshotName":"photo-linux-firefox-144.0.2-tess-clicks-on-input-field-b5684dfac4.png","timeStamp":1767647442178},{"screenshot":"photo-linux-firefox-144.0.2-tess-clicks-on-input-field-efa577c7f4.png","screenshotName":"photo-linux-firefox-144.0.2-tess-clicks-on-input-field-efa577c7f4.png","timeStamp":1767647442199},{"screenshot":"photo-linux-firefox-144.0.2-tess-clicks-on-input-field-96b7c7caf7.png","screenshotName":"photo-linux-firefox-144.0.2-tess-clicks-on-input-field-96b7c7caf7.png","timeStamp":1767647442227}],"duration":74,"result":"SUCCESS"},{"number":35,"description":"Tess waits until page element located by css (&apos;.dropdown-available-options&apos;) does become visible","startTime":"2026-01-05T21:10:42.234Z","children":[],"reportData":[],"screenshots":[{"screenshot":"photo-linux-firefox-144.0.2-tess-waits-until-page-element-located-by-c-5bc32f17f6.png","screenshotName":"photo-linux-firefox-144.0.2-tess-waits-until-page-element-located-by-c-5bc32f17f6.png","timeStamp":1767647442289},{"screenshot":"photo-linux-firefox-144.0.2-tess-waits-until-page-element-located-by-c-38d67e0cb3.png","screenshotName":"photo-linux-firefox-144.0.2-tess-waits-until-page-element-located-by-c-38d67e0cb3.png","timeStamp":1767647442307},{"screenshot":"photo-linux-firefox-144.0.2-tess-waits-until-page-element-located-by-c-1fe79174c6.png","screenshotName":"photo-linux-firefox-144.0.2-tess-waits-until-page-element-located-by-c-1fe79174c6.png","timeStamp":1767647442325},{"screenshot":"photo-linux-firefox-144.0.2-tess-waits-until-page-element-located-by-c-42a619457d.png","screenshotName":"photo-linux-firefox-144.0.2-tess-waits-until-page-element-located-by-c-42a619457d.png","timeStamp":1767647442346},{"screenshot":"photo-linux-firefox-144.0.2-tess-waits-until-page-element-located-by-c-549379eef1.png","screenshotName":"photo-linux-firefox-144.0.2-tess-waits-until-page-element-located-by-c-549379eef1.png","timeStamp":1767647442366},{"screenshot":"photo-linux-firefox-144.0.2-tess-waits-until-page-element-located-by-c-e98a99f679.png","screenshotName":"photo-linux-firefox-144.0.2-tess-waits-until-page-element-located-by-c-e98a99f679.png","timeStamp":1767647442387}],"duration":31,"result":"SUCCESS"}],"reportData":[],"screenshots":[],"duration":407,"result":"SUCCESS"}],"reportData":[],"screenshots":[],"duration":418,"result":"SUCCESS"},{"number":36,"description":"Tess clicks on the first of page elements located by css (&apos;.dropdown-available-option&apos;) of page element located by css (&apos;.dropdown-available-options&apos;) where Text does include &quot;First&quot;","startTime":"2026-01-05T21:10:42.417Z","children":[],"reportData":[],"screenshots":[{"screenshot":"photo-linux-firefox-144.0.2-tess-clicks-on-the-first-of-page-elements-909b65146d.png","screenshotName":"photo-linux-firefox-144.0.2-tess-clicks-on-the-first-of-page-elements-909b65146d.png","timeStamp":1767647442582},{"screenshot":"photo-linux-firefox-144.0.2-tess-clicks-on-the-first-of-page-elements-b91eff3535.png","screenshotName":"photo-linux-firefox-144.0.2-tess-clicks-on-the-first-of-page-elements-b91eff3535.png","timeStamp":1767647442599},{"screenshot":"photo-linux-firefox-144.0.2-tess-clicks-on-the-first-of-page-elements-e8a45bdecc.png","screenshotName":"photo-linux-firefox-144.0.2-tess-clicks-on-the-first-of-page-elements-e8a45bdecc.png","timeStamp":1767647442620},{"screenshot":"photo-linux-firefox-144.0.2-tess-clicks-on-the-first-of-page-elements-dd3b2a8fb0.png","screenshotName":"photo-linux-firefox-144.0.2-tess-clicks-on-the-first-of-page-elements-dd3b2a8fb0.png","timeStamp":1767647442638},{"screenshot":"photo-linux-firefox-144.0.2-tess-clicks-on-the-first-of-page-elements-aefafe24f6.png","screenshotName":"photo-linux-firefox-144.0.2-tess-clicks-on-the-first-of-page-elements-aefafe24f6.png","timeStamp":1767647442656},{"screenshot":"photo-linux-firefox-144.0.2-tess-clicks-on-the-first-of-page-elements-69ba716a90.png","screenshotName":"photo-linux-firefox-144.0.2-tess-clicks-on-the-first-of-page-elements-69ba716a90.png","timeStamp":1767647442673}],"duration":145,"result":"SUCCESS"},{"number":37,"description":"Tess ensures that the text of page elements located by css (&apos;.dropdown-selected-option&apos;) of input field does contain at least one item that does start with &quot;First&quot;","startTime":"2026-01-05T21:10:42.679Z","children":[],"reportData":[],"screenshots":[{"screenshot":"photo-linux-firefox-144.0.2-tess-ensures-that-the-text-of-page-element-a19a2f89c2.png","screenshotName":"photo-linux-firefox-144.0.2-tess-ensures-that-the-text-of-page-element-a19a2f89c2.png","timeStamp":1767647442708},{"screenshot":"photo-linux-firefox-144.0.2-tess-ensures-that-the-text-of-page-element-cdfd0e854b.png","screenshotName":"photo-linux-firefox-144.0.2-tess-ensures-that-the-text-of-page-element-cdfd0e854b.png","timeStamp":1767647442726},{"screenshot":"photo-linux-firefox-144.0.2-tess-ensures-that-the-text-of-page-element-eaad836b49.png","screenshotName":"photo-linux-firefox-144.0.2-tess-ensures-that-the-text-of-page-element-eaad836b49.png","timeStamp":1767647442744},{"screenshot":"photo-linux-firefox-144.0.2-tess-ensures-that-the-text-of-page-element-6aec18c09e.png","screenshotName":"photo-linux-firefox-144.0.2-tess-ensures-that-the-text-of-page-element-6aec18c09e.png","timeStamp":1767647442762},{"screenshot":"photo-linux-firefox-144.0.2-tess-ensures-that-the-text-of-page-element-3d5c1350ce.png","screenshotName":"photo-linux-firefox-144.0.2-tess-ensures-that-the-text-of-page-element-3d5c1350ce.png","timeStamp":1767647442780},{"screenshot":"photo-linux-firefox-144.0.2-tess-ensures-that-the-text-of-page-element-d7f7e0306e.png","screenshotName":"photo-linux-firefox-144.0.2-tess-ensures-that-the-text-of-page-element-d7f7e0306e.png","timeStamp":1767647442797}],"duration":11,"result":"SUCCESS"}],"reportData":[],"screenshots":[],"duration":814,"result":"SUCCESS"},{"number":38,"description":"Tess selects &apos;Second&apos; from dropdown","startTime":"2026-01-05T21:10:42.831Z","children":[{"number":39,"description":"Tess opens the dropdown","startTime":"2026-01-05T21:10:42.832Z","children":[{"number":40,"description":"Tess checks whether CSS classes of dropdown does not contain &quot;dropdown-expanded&quot;","startTime":"2026-01-05T21:10:42.832Z","children":[{"number":41,"description":"Tess clicks on input field","startTime":"2026-01-05T21:10:42.840Z","children":[],"reportData":[],"screenshots":[{"screenshot":"photo-linux-firefox-144.0.2-tess-clicks-on-input-field-77c4a96b81.png","screenshotName":"photo-linux-firefox-144.0.2-tess-clicks-on-input-field-77c4a96b81.png","timeStamp":1767647442944},{"screenshot":"photo-linux-firefox-144.0.2-tess-clicks-on-input-field-134db4b814.png","screenshotName":"photo-linux-firefox-144.0.2-tess-clicks-on-input-field-134db4b814.png","timeStamp":1767647442962},{"screenshot":"photo-linux-firefox-144.0.2-tess-clicks-on-input-field-cdbe48345e.png","screenshotName":"photo-linux-firefox-144.0.2-tess-clicks-on-input-field-cdbe48345e.png","timeStamp":1767647442980},{"screenshot":"photo-linux-firefox-144.0.2-tess-clicks-on-input-field-7c1ec92532.png","screenshotName":"photo-linux-firefox-144.0.2-tess-clicks-on-input-field-7c1ec92532.png","timeStamp":1767647443000},{"screenshot":"photo-linux-firefox-144.0.2-tess-clicks-on-input-field-a3e4beb728.png","screenshotName":"photo-linux-firefox-144.0.2-tess-clicks-on-input-field-a3e4beb728.png","timeStamp":1767647443017},{"screenshot":"photo-linux-firefox-144.0.2-tess-clicks-on-input-field-0039cd1c24.png","screenshotName":"photo-linux-firefox-144.0.2-tess-clicks-on-input-field-0039cd1c24.png","timeStamp":1767647443034}],"duration":83,"result":"SUCCESS"},{"number":42,"description":"Tess waits until page element located by css (&apos;.dropdown-available-options&apos;) does become visible","startTime":"2026-01-05T21:10:43.038Z","children":[],"reportData":[],"screenshots":[{"screenshot":"photo-linux-firefox-144.0.2-tess-waits-until-page-element-located-by-c-93af7b8d24.png","screenshotName":"photo-linux-firefox-144.0.2-tess-waits-until-page-element-located-by-c-93af7b8d24.png","timeStamp":1767647443087},{"screenshot":"photo-linux-firefox-144.0.2-tess-waits-until-page-element-located-by-c-cb580777db.png","screenshotName":"photo-linux-firefox-144.0.2-tess-waits-until-page-element-located-by-c-cb580777db.png","timeStamp":1767647443105},{"screenshot":"photo-linux-firefox-144.0.2-tess-waits-until-page-element-located-by-c-29ae97a67e.png","screenshotName":"photo-linux-firefox-144.0.2-tess-waits-until-page-element-located-by-c-29ae97a67e.png","timeStamp":1767647443122},{"screenshot":"photo-linux-firefox-144.0.2-tess-waits-until-page-element-located-by-c-4fcfdb290d.png","screenshotName":"photo-linux-firefox-144.0.2-tess-waits-until-page-element-located-by-c-4fcfdb290d.png","timeStamp":1767647443166},{"screenshot":"photo-linux-firefox-144.0.2-tess-waits-until-page-element-located-by-c-1945d6336f.png","screenshotName":"photo-linux-firefox-144.0.2-tess-waits-until-page-element-located-by-c-1945d6336f.png","timeStamp":1767647443186},{"screenshot":"photo-linux-firefox-144.0.2-tess-waits-until-page-element-located-by-c-375b9cda77.png","screenshotName":"photo-linux-firefox-144.0.2-tess-waits-until-page-element-located-by-c-375b9cda77.png","timeStamp":1767647443141}],"duration":29,"result":"SUCCESS"}],"reportData":[],"screenshots":[],"duration":358,"result":"SUCCESS"}],"reportData":[],"screenshots":[],"duration":368,"result":"SUCCESS"},{"number":43,"description":"Tess clicks on the first of page elements located by css (&apos;.dropdown-available-option&apos;) of page element located by css (&apos;.dropdown-available-options&apos;) where Text does include &quot;Second&quot;","startTime":"2026-01-05T21:10:43.211Z","children":[],"reportData":[],"screenshots":[{"screenshot":"photo-linux-firefox-144.0.2-tess-clicks-on-the-first-of-page-elements-c8554ac70c.png","screenshotName":"photo-linux-firefox-144.0.2-tess-clicks-on-the-first-of-page-elements-c8554ac70c.png","timeStamp":1767647443344},{"screenshot":"photo-linux-firefox-144.0.2-tess-clicks-on-the-first-of-page-elements-aa44de7e0c.png","screenshotName":"photo-linux-firefox-144.0.2-tess-clicks-on-the-first-of-page-elements-aa44de7e0c.png","timeStamp":1767647443363},{"screenshot":"photo-linux-firefox-144.0.2-tess-clicks-on-the-first-of-page-elements-462cf668e0.png","screenshotName":"photo-linux-firefox-144.0.2-tess-clicks-on-the-first-of-page-elements-462cf668e0.png","timeStamp":1767647443382},{"screenshot":"photo-linux-firefox-144.0.2-tess-clicks-on-the-first-of-page-elements-e7ec1fe125.png","screenshotName":"photo-linux-firefox-144.0.2-tess-clicks-on-the-first-of-page-elements-e7ec1fe125.png","timeStamp":1767647443400},{"screenshot":"photo-linux-firefox-144.0.2-tess-clicks-on-the-first-of-page-elements-5fc742a962.png","screenshotName":"photo-linux-firefox-144.0.2-tess-clicks-on-the-first-of-page-elements-5fc742a962.png","timeStamp":1767647443419},{"screenshot":"photo-linux-firefox-144.0.2-tess-clicks-on-the-first-of-page-elements-3b17765017.png","screenshotName":"photo-linux-firefox-144.0.2-tess-clicks-on-the-first-of-page-elements-3b17765017.png","timeStamp":1767647443437}],"duration":114,"result":"SUCCESS"},{"number":44,"description":"Tess ensures that the text of page elements located by css (&apos;.dropdown-selected-option&apos;) of input field does contain at least one item that does start with &quot;Second&quot;","startTime":"2026-01-05T21:10:43.448Z","children":[],"reportData":[],"screenshots":[{"screenshot":"photo-linux-firefox-144.0.2-tess-ensures-that-the-text-of-page-element-abf4a95d04.png","screenshotName":"photo-linux-firefox-144.0.2-tess-ensures-that-the-text-of-page-element-abf4a95d04.png","timeStamp":1767647443481},{"screenshot":"photo-linux-firefox-144.0.2-tess-ensures-that-the-text-of-page-element-7ee1e5c32c.png","screenshotName":"photo-linux-firefox-144.0.2-tess-ensures-that-the-text-of-page-element-7ee1e5c32c.png","timeStamp":1767647443500},{"screenshot":"photo-linux-firefox-144.0.2-tess-ensures-that-the-text-of-page-element-635d34cd7d.png","screenshotName":"photo-linux-firefox-144.0.2-tess-ensures-that-the-text-of-page-element-635d34cd7d.png","timeStamp":1767647443517},{"screenshot":"photo-linux-firefox-144.0.2-tess-ensures-that-the-text-of-page-element-797c3020ef.png","screenshotName":"photo-linux-firefox-144.0.2-tess-ensures-that-the-text-of-page-element-797c3020ef.png","timeStamp":1767647443536},{"screenshot":"photo-linux-firefox-144.0.2-tess-ensures-that-the-text-of-page-element-2a637064f4.png","screenshotName":"photo-linux-firefox-144.0.2-tess-ensures-that-the-text-of-page-element-2a637064f4.png","timeStamp":1767647443553},{"screenshot":"photo-linux-firefox-144.0.2-tess-ensures-that-the-text-of-page-element-5b7b4a8e03.png","screenshotName":"photo-linux-firefox-144.0.2-tess-ensures-that-the-text-of-page-element-5b7b4a8e03.png","timeStamp":1767647443571}],"duration":14,"result":"SUCCESS"}],"reportData":[],"screenshots":[],"duration":745,"result":"SUCCESS"}],"reportData":[],"screenshots":[],"duration":1611,"result":"SUCCESS"}],"reportData":[],"screenshots":[],"duration":1622,"result":"SUCCESS"},{"number":45,"description":"Tess deselects [ &apos;First&apos;, &apos;Second&apos; ] from dropdown","startTime":"2026-01-05T21:10:43.608Z","children":[{"number":46,"description":"Tess iterates over [ &apos;First&apos;, &apos;Second&apos; ]","startTime":"2026-01-05T21:10:43.608Z","children":[{"number":47,"description":"Tess deselects &apos;First&apos; from dropdown","startTime":"2026-01-05T21:10:43.616Z","children":[{"number":48,"description":"Tess clicks on deselect button of the first of page elements located by css (&apos;.dropdown-selected-option&apos;) of input field where Text does include &quot;First&quot;","startTime":"2026-01-05T21:10:43.617Z","children":[],"reportData":[],"screenshots":[{"screenshot":"photo-linux-firefox-144.0.2-tess-clicks-on-deselect-button-of-the-firs-d43276c05d.png","screenshotName":"photo-linux-firefox-144.0.2-tess-clicks-on-deselect-button-of-the-firs-d43276c05d.png","timeStamp":1767647443743},{"screenshot":"photo-linux-firefox-144.0.2-tess-clicks-on-deselect-button-of-the-firs-cc35ced5d3.png","screenshotName":"photo-linux-firefox-144.0.2-tess-clicks-on-deselect-button-of-the-firs-cc35ced5d3.png","timeStamp":1767647443761},{"screenshot":"photo-linux-firefox-144.0.2-tess-clicks-on-deselect-button-of-the-firs-7189bb6700.png","screenshotName":"photo-linux-firefox-144.0.2-tess-clicks-on-deselect-button-of-the-firs-7189bb6700.png","timeStamp":1767647443779},{"screenshot":"photo-linux-firefox-144.0.2-tess-clicks-on-deselect-button-of-the-firs-5ef2b0fe2a.png","screenshotName":"photo-linux-firefox-144.0.2-tess-clicks-on-deselect-button-of-the-firs-5ef2b0fe2a.png","timeStamp":1767647443797},{"screenshot":"photo-linux-firefox-144.0.2-tess-clicks-on-deselect-button-of-the-firs-304abcd6fc.png","screenshotName":"photo-linux-firefox-144.0.2-tess-clicks-on-deselect-button-of-the-firs-304abcd6fc.png","timeStamp":1767647443814},{"screenshot":"photo-linux-firefox-144.0.2-tess-clicks-on-deselect-button-of-the-firs-de52cd859b.png","screenshotName":"photo-linux-firefox-144.0.2-tess-clicks-on-deselect-button-of-the-firs-de52cd859b.png","timeStamp":1767647443832}],"duration":107,"result":"SUCCESS"},{"number":49,"description":"Tess ensures that the text of page elements located by css (&apos;.dropdown-selected-option&apos;) of input field does not contain &quot;First&quot;","startTime":"2026-01-05T21:10:43.841Z","children":[],"reportData":[],"screenshots":[{"screenshot":"photo-linux-firefox-144.0.2-tess-ensures-that-the-text-of-page-element-de52cd859b.png","screenshotName":"photo-linux-firefox-144.0.2-tess-ensures-that-the-text-of-page-element-de52cd859b.png","timeStamp":1767647443868},{"screenshot":"photo-linux-firefox-144.0.2-tess-ensures-that-the-text-of-page-element-de52cd859b.png","screenshotName":"photo-linux-firefox-144.0.2-tess-ensures-that-the-text-of-page-element-de52cd859b.png","timeStamp":1767647443885},{"screenshot":"photo-linux-firefox-144.0.2-tess-ensures-that-the-text-of-page-element-de52cd859b.png","screenshotName":"photo-linux-firefox-144.0.2-tess-ensures-that-the-text-of-page-element-de52cd859b.png","timeStamp":1767647443902},{"screenshot":"photo-linux-firefox-144.0.2-tess-ensures-that-the-text-of-page-element-de52cd859b.png","screenshotName":"photo-linux-firefox-144.0.2-tess-ensures-that-the-text-of-page-element-de52cd859b.png","timeStamp":1767647443920},{"screenshot":"photo-linux-firefox-144.0.2-tess-ensures-that-the-text-of-page-element-de52cd859b.png","screenshotName":"photo-linux-firefox-144.0.2-tess-ensures-that-the-text-of-page-element-de52cd859b.png","timeStamp":1767647443939},{"screenshot":"photo-linux-firefox-144.0.2-tess-ensures-that-the-text-of-page-element-de52cd859b.png","screenshotName":"photo-linux-firefox-144.0.2-tess-ensures-that-the-text-of-page-element-de52cd859b.png","timeStamp":1767647443956}],"duration":8,"result":"SUCCESS"}],"reportData":[],"screenshots":[],"duration":346,"result":"SUCCESS"},{"number":50,"description":"Tess deselects &apos;Second&apos; from dropdown","startTime":"2026-01-05T21:10:43.987Z","children":[{"number":51,"description":"Tess clicks on deselect button of the first of page elements located by css (&apos;.dropdown-selected-option&apos;) of input field where Text does include &quot;Second&quot;","startTime":"2026-01-05T21:10:43.988Z","children":[],"reportData":[],"screenshots":[{"screenshot":"photo-linux-firefox-144.0.2-tess-clicks-on-deselect-button-of-the-firs-02eb5d3536.png","screenshotName":"photo-linux-firefox-144.0.2-tess-clicks-on-deselect-button-of-the-firs-02eb5d3536.png","timeStamp":1767647444094},{"screenshot":"photo-linux-firefox-144.0.2-tess-clicks-on-deselect-button-of-the-firs-02eb5d3536.png","screenshotName":"photo-linux-firefox-144.0.2-tess-clicks-on-deselect-button-of-the-firs-02eb5d3536.png","timeStamp":1767647444111},{"screenshot":"photo-linux-firefox-144.0.2-tess-clicks-on-deselect-button-of-the-firs-02eb5d3536.png","screenshotName":"photo-linux-firefox-144.0.2-tess-clicks-on-deselect-button-of-the-firs-02eb5d3536.png","timeStamp":1767647444128},{"screenshot":"photo-linux-firefox-144.0.2-tess-clicks-on-deselect-button-of-the-firs-02eb5d3536.png","screenshotName":"photo-linux-firefox-144.0.2-tess-clicks-on-deselect-button-of-the-firs-02eb5d3536.png","timeStamp":1767647444145},{"screenshot":"photo-linux-firefox-144.0.2-tess-clicks-on-deselect-button-of-the-firs-02eb5d3536.png","screenshotName":"photo-linux-firefox-144.0.2-tess-clicks-on-deselect-button-of-the-firs-02eb5d3536.png","timeStamp":1767647444172},{"screenshot":"photo-linux-firefox-144.0.2-tess-clicks-on-deselect-button-of-the-firs-02eb5d3536.png","screenshotName":"photo-linux-firefox-144.0.2-tess-clicks-on-deselect-button-of-the-firs-02eb5d3536.png","timeStamp":1767647444190}],"duration":86,"result":"SUCCESS"},{"number":52,"description":"Tess ensures that the text of page elements located by css (&apos;.dropdown-selected-option&apos;) of input field does not contain &quot;Second&quot;","startTime":"2026-01-05T21:10:44.200Z","children":[],"reportData":[],"screenshots":[{"screenshot":"photo-linux-firefox-144.0.2-tess-ensures-that-the-text-of-page-element-02eb5d3536.png","screenshotName":"photo-linux-firefox-144.0.2-tess-ensures-that-the-text-of-page-element-02eb5d3536.png","timeStamp":1767647444223},{"screenshot":"photo-linux-firefox-144.0.2-tess-ensures-that-the-text-of-page-element-02eb5d3536.png","screenshotName":"photo-linux-firefox-144.0.2-tess-ensures-that-the-text-of-page-element-02eb5d3536.png","timeStamp":1767647444244},{"screenshot":"photo-linux-firefox-144.0.2-tess-ensures-that-the-text-of-page-element-02eb5d3536.png","screenshotName":"photo-linux-firefox-144.0.2-tess-ensures-that-the-text-of-page-element-02eb5d3536.png","timeStamp":1767647444261},{"screenshot":"photo-linux-firefox-144.0.2-tess-ensures-that-the-text-of-page-element-02eb5d3536.png","screenshotName":"photo-linux-firefox-144.0.2-tess-ensures-that-the-text-of-page-element-02eb5d3536.png","timeStamp":1767647444279},{"screenshot":"photo-linux-firefox-144.0.2-tess-ensures-that-the-text-of-page-element-02eb5d3536.png","screenshotName":"photo-linux-firefox-144.0.2-tess-ensures-that-the-text-of-page-element-02eb5d3536.png","timeStamp":1767647444295},{"screenshot":"photo-linux-firefox-144.0.2-tess-ensures-that-the-text-of-page-element-02eb5d3536.png","screenshotName":"photo-linux-firefox-144.0.2-tess-ensures-that-the-text-of-page-element-02eb5d3536.png","timeStamp":1767647444311}],"duration":5,"result":"SUCCESS"}],"reportData":[],"screenshots":[],"duration":331,"result":"SUCCESS"}],"reportData":[],"screenshots":[],"duration":720,"result":"SUCCESS"}],"reportData":[],"screenshots":[],"duration":731,"result":"SUCCESS"},{"number":53,"description":"Tess ensures that 0 does equal 0","startTime":"2026-01-05T21:10:44.355Z","children":[],"reportData":[],"screenshots":[{"screenshot":"photo-linux-firefox-144.0.2-tess-ensures-that-0-does-equal-0-02eb5d3536.png","screenshotName":"photo-linux-firefox-144.0.2-tess-ensures-that-0-does-equal-0-02eb5d3536.png","timeStamp":1767647444384},{"screenshot":"photo-linux-firefox-144.0.2-tess-ensures-that-0-does-equal-0-02eb5d3536.png","screenshotName":"photo-linux-firefox-144.0.2-tess-ensures-that-0-does-equal-0-02eb5d3536.png","timeStamp":1767647444401},{"screenshot":"photo-linux-firefox-144.0.2-tess-ensures-that-0-does-equal-0-02eb5d3536.png","screenshotName":"photo-linux-firefox-144.0.2-tess-ensures-that-0-does-equal-0-02eb5d3536.png","timeStamp":1767647444419},{"screenshot":"photo-linux-firefox-144.0.2-tess-ensures-that-0-does-equal-0-02eb5d3536.png","screenshotName":"photo-linux-firefox-144.0.2-tess-ensures-that-0-does-equal-0-02eb5d3536.png","timeStamp":1767647444437},{"screenshot":"photo-linux-firefox-144.0.2-tess-ensures-that-0-does-equal-0-02eb5d3536.png","screenshotName":"photo-linux-firefox-144.0.2-tess-ensures-that-0-does-equal-0-02eb5d3536.png","timeStamp":1767647444453},{"screenshot":"photo-linux-firefox-144.0.2-tess-ensures-that-0-does-equal-0-02eb5d3536.png","screenshotName":"photo-linux-firefox-144.0.2-tess-ensures-that-0-does-equal-0-02eb5d3536.png","timeStamp":1767647444471}],"duration":10,"result":"SUCCESS"},{"number":54,"description":"Tess ensures that placeholder of dropdown does equal &quot;Select option&quot;","startTime":"2026-01-05T21:10:44.478Z","children":[],"reportData":[],"screenshots":[{"screenshot":"photo-linux-firefox-144.0.2-tess-ensures-that-placeholder-of-dropdown-02eb5d3536.png","screenshotName":"photo-linux-firefox-144.0.2-tess-ensures-that-placeholder-of-dropdown-02eb5d3536.png","timeStamp":1767647444504},{"screenshot":"photo-linux-firefox-144.0.2-tess-ensures-that-placeholder-of-dropdown-02eb5d3536.png","screenshotName":"photo-linux-firefox-144.0.2-tess-ensures-that-placeholder-of-dropdown-02eb5d3536.png","timeStamp":1767647444521},{"screenshot":"photo-linux-firefox-144.0.2-tess-ensures-that-placeholder-of-dropdown-02eb5d3536.png","screenshotName":"photo-linux-firefox-144.0.2-tess-ensures-that-placeholder-of-dropdown-02eb5d3536.png","timeStamp":1767647444539},{"screenshot":"photo-linux-firefox-144.0.2-tess-ensures-that-placeholder-of-dropdown-02eb5d3536.png","screenshotName":"photo-linux-firefox-144.0.2-tess-ensures-that-placeholder-of-dropdown-02eb5d3536.png","timeStamp":1767647444556},{"screenshot":"photo-linux-firefox-144.0.2-tess-ensures-that-placeholder-of-dropdown-02eb5d3536.png","screenshotName":"photo-linux-firefox-144.0.2-tess-ensures-that-placeholder-of-dropdown-02eb5d3536.png","timeStamp":1767647444575},{"screenshot":"photo-linux-firefox-144.0.2-tess-ensures-that-placeholder-of-dropdown-02eb5d3536.png","screenshotName":"photo-linux-firefox-144.0.2-tess-ensures-that-placeholder-of-dropdown-02eb5d3536.png","timeStamp":1767647444591}],"duration":7,"result":"SUCCESS"}],"reportData":[],"screenshots":[],"duration":2966,"result":"SUCCESS"},{"number":55,"description":"goes back to showing the placeholder when all the selected options get deselected #3 - Retries: Attempt #1","startTime":"2026-01-05T21:11:19.319Z","children":[{"number":56,"description":"Tess selects [ &apos;First&apos;, &apos;Second&apos; ] from dropdown","startTime":"2026-01-05T21:11:19.475Z","children":[{"number":57,"description":"Tess iterates over [ &apos;First&apos;, &apos;Second&apos; ]","startTime":"2026-01-05T21:11:19.476Z","children":[{"number":58,"description":"Tess selects &apos;First&apos; from dropdown","startTime":"2026-01-05T21:11:19.490Z","children":[{"number":59,"description":"Tess opens the dropdown","startTime":"2026-01-05T21:11:19.490Z","children":[{"number":60,"description":"Tess checks whether CSS classes of dropdown does not contain &quot;dropdown-expanded&quot;","startTime":"2026-01-05T21:11:19.491Z","children":[{"number":61,"description":"Tess clicks on input field","startTime":"2026-01-05T21:11:19.505Z","children":[],"reportData":[],"screenshots":[{"screenshot":"photo-linux-webkit-26.0-tess-clicks-on-input-field-0cc5cbd933.png","screenshotName":"photo-linux-webkit-26.0-tess-clicks-on-input-field-0cc5cbd933.png","timeStamp":1767647479723},{"screenshot":"photo-linux-webkit-26.0-tess-clicks-on-input-field-0f09325194.png","screenshotName":"photo-linux-webkit-26.0-tess-clicks-on-input-field-0f09325194.png","timeStamp":1767647479968}],"duration":76,"result":"SUCCESS"},{"number":62,"description":"Tess waits until page element located by css (&apos;.dropdown-available-options&apos;) does become visible","startTime":"2026-01-05T21:11:19.980Z","children":[],"reportData":[],"screenshots":[{"screenshot":"photo-linux-webkit-26.0-tess-waits-until-page-element-located-by-css-ce2bbfb638.png","screenshotName":"photo-linux-webkit-26.0-tess-waits-until-page-element-located-by-css-ce2bbfb638.png","timeStamp":1767647480227},{"screenshot":"photo-linux-webkit-26.0-tess-waits-until-page-element-located-by-css-85ef545815.png","screenshotName":"photo-linux-webkit-26.0-tess-waits-until-page-element-located-by-css-85ef545815.png","timeStamp":1767647480385}],"duration":57,"result":"SUCCESS"}],"reportData":[],"screenshots":[],"duration":900,"result":"SUCCESS"}],"reportData":[],"screenshots":[],"duration":911,"result":"SUCCESS"},{"number":63,"description":"Tess clicks on the first of page elements located by css (&apos;.dropdown-available-option&apos;) of page element located by css (&apos;.dropdown-available-options&apos;) where Text does include &quot;First&quot;","startTime":"2026-01-05T21:11:20.412Z","children":[],"reportData":[],"screenshots":[{"screenshot":"photo-linux-webkit-26.0-tess-clicks-on-the-first-of-page-elements-loca-84d66ac93f.png","screenshotName":"photo-linux-webkit-26.0-tess-clicks-on-the-first-of-page-elements-loca-84d66ac93f.png","timeStamp":1767647480637},{"screenshot":"photo-linux-webkit-26.0-tess-clicks-on-the-first-of-page-elements-loca-84d66ac93f.png","screenshotName":"photo-linux-webkit-26.0-tess-clicks-on-the-first-of-page-elements-loca-84d66ac93f.png","timeStamp":1767647480882}],"duration":82,"result":"SUCCESS"},{"number":64,"description":"Tess ensures that the text of page elements located by css (&apos;.dropdown-selected-option&apos;) of input field does contain at least one item that does start with &quot;First&quot;","startTime":"2026-01-05T21:11:20.886Z","children":[],"reportData":[],"screenshots":[{"screenshot":"photo-linux-webkit-26.0-tess-ensures-that-the-text-of-page-elements-lo-946ea74e24.png","screenshotName":"photo-linux-webkit-26.0-tess-ensures-that-the-text-of-page-elements-lo-946ea74e24.png","timeStamp":1767647481161},{"screenshot":"photo-linux-webkit-26.0-tess-ensures-that-the-text-of-page-elements-lo-0d5e9aaf98.png","screenshotName":"photo-linux-webkit-26.0-tess-ensures-that-the-text-of-page-elements-lo-0d5e9aaf98.png","timeStamp":1767647481307}],"duration":15,"result":"SUCCESS"}],"reportData":[],"screenshots":[],"duration":1827,"result":"SUCCESS"},{"number":65,"description":"Tess selects &apos;Second&apos; from dropdown","startTime":"2026-01-05T21:11:21.346Z","children":[{"number":66,"description":"Tess opens the dropdown","startTime":"2026-01-05T21:11:21.346Z","children":[{"number":67,"description":"Tess checks whether CSS classes of dropdown does not contain &quot;dropdown-expanded&quot;","startTime":"2026-01-05T21:11:21.347Z","children":[{"number":68,"description":"Tess clicks on input field","startTime":"2026-01-05T21:11:21.354Z","children":[],"reportData":[],"screenshots":[{"screenshot":"photo-linux-webkit-26.0-tess-clicks-on-input-field-92f87d22eb.png","screenshotName":"photo-linux-webkit-26.0-tess-clicks-on-input-field-92f87d22eb.png","timeStamp":1767647481561},{"screenshot":"photo-linux-webkit-26.0-tess-clicks-on-input-field-92f87d22eb.png","screenshotName":"photo-linux-webkit-26.0-tess-clicks-on-input-field-92f87d22eb.png","timeStamp":1767647481798}],"duration":63,"result":"SUCCESS"},{"number":69,"description":"Tess waits until page element located by css (&apos;.dropdown-available-options&apos;) does become visible","startTime":"2026-01-05T21:11:21.805Z","children":[],"reportData":[],"screenshots":[{"screenshot":"photo-linux-webkit-26.0-tess-waits-until-page-element-located-by-css-75bdbae4a6.png","screenshotName":"photo-linux-webkit-26.0-tess-waits-until-page-element-located-by-css-75bdbae4a6.png","timeStamp":1767647482074},{"screenshot":"photo-linux-webkit-26.0-tess-waits-until-page-element-located-by-css-6ad3c4d254.png","screenshotName":"photo-linux-webkit-26.0-tess-waits-until-page-element-located-by-css-6ad3c4d254.png","timeStamp":1767647482228}],"duration":35,"result":"SUCCESS"}],"reportData":[],"screenshots":[],"duration":883,"result":"SUCCESS"}],"reportData":[],"screenshots":[],"duration":894,"result":"SUCCESS"},{"number":70,"description":"Tess clicks on the first of page elements located by css (&apos;.dropdown-available-option&apos;) of page element located by css (&apos;.dropdown-available-options&apos;) where Text does include &quot;Second&quot;","startTime":"2026-01-05T21:11:22.251Z","children":[],"reportData":[],"screenshots":[{"screenshot":"photo-linux-webkit-26.0-tess-clicks-on-the-first-of-page-elements-loca-bc701de097.png","screenshotName":"photo-linux-webkit-26.0-tess-clicks-on-the-first-of-page-elements-loca-bc701de097.png","timeStamp":1767647482484},{"screenshot":"photo-linux-webkit-26.0-tess-clicks-on-the-first-of-page-elements-loca-bc701de097.png","screenshotName":"photo-linux-webkit-26.0-tess-clicks-on-the-first-of-page-elements-loca-bc701de097.png","timeStamp":1767647482726}],"duration":90,"result":"SUCCESS"},{"number":71,"description":"Tess ensures that the text of page elements located by css (&apos;.dropdown-selected-option&apos;) of input field does contain at least one item that does start with &quot;Second&quot;","startTime":"2026-01-05T21:11:22.731Z","children":[],"reportData":[],"screenshots":[{"screenshot":"photo-linux-webkit-26.0-tess-ensures-that-the-text-of-page-elements-lo-0ca7419f8a.png","screenshotName":"photo-linux-webkit-26.0-tess-ensures-that-the-text-of-page-elements-lo-0ca7419f8a.png","timeStamp":1767647482983},{"screenshot":"photo-linux-webkit-26.0-tess-ensures-that-the-text-of-page-elements-lo-4a9b8eea42.png","screenshotName":"photo-linux-webkit-26.0-tess-ensures-that-the-text-of-page-elements-lo-4a9b8eea42.png","timeStamp":1767647483135}],"duration":20,"result":"SUCCESS"}],"reportData":[],"screenshots":[],"duration":1790,"result":"SUCCESS"}],"reportData":[],"screenshots":[],"duration":3671,"result":"SUCCESS"}],"reportData":[],"screenshots":[],"duration":3683,"result":"SUCCESS"},{"number":72,"description":"Tess deselects [ &apos;First&apos;, &apos;Second&apos; ] from dropdown","startTime":"2026-01-05T21:11:23.169Z","children":[{"number":73,"description":"Tess iterates over [ &apos;First&apos;, &apos;Second&apos; ]","startTime":"2026-01-05T21:11:23.169Z","children":[{"number":74,"description":"Tess deselects &apos;First&apos; from dropdown","startTime":"2026-01-05T21:11:23.183Z","children":[{"number":75,"description":"Tess clicks on deselect button of the first of page elements located by css (&apos;.dropdown-selected-option&apos;) of input field where Text does include &quot;First&quot;","startTime":"2026-01-05T21:11:23.184Z","children":[],"reportData":[],"screenshots":[{"screenshot":"photo-linux-webkit-26.0-tess-clicks-on-deselect-button-of-the-first-of-e602ad9359.png","screenshotName":"photo-linux-webkit-26.0-tess-clicks-on-deselect-button-of-the-first-of-e602ad9359.png","timeStamp":1767647483561},{"screenshot":"photo-linux-webkit-26.0-tess-clicks-on-deselect-button-of-the-first-of-e602ad9359.png","screenshotName":"photo-linux-webkit-26.0-tess-clicks-on-deselect-button-of-the-first-of-e602ad9359.png","timeStamp":1767647483412}],"duration":85,"result":"SUCCESS"},{"number":76,"description":"Tess ensures that the text of page elements located by css (&apos;.dropdown-selected-option&apos;) of input field does not contain &quot;First&quot;","startTime":"2026-01-05T21:11:23.563Z","children":[],"reportData":[],"screenshots":[{"screenshot":"photo-linux-webkit-26.0-tess-ensures-that-the-text-of-page-elements-lo-e602ad9359.png","screenshotName":"photo-linux-webkit-26.0-tess-ensures-that-the-text-of-page-elements-lo-e602ad9359.png","timeStamp":1767647483850},{"screenshot":"photo-linux-webkit-26.0-tess-ensures-that-the-text-of-page-elements-lo-e602ad9359.png","screenshotName":"photo-linux-webkit-26.0-tess-ensures-that-the-text-of-page-elements-lo-e602ad9359.png","timeStamp":1767647483711}],"duration":8,"result":"SUCCESS"}],"reportData":[],"screenshots":[],"duration":670,"result":"SUCCESS"},{"number":77,"description":"Tess deselects &apos;Second&apos; from dropdown","startTime":"2026-01-05T21:11:23.877Z","children":[{"number":78,"description":"Tess clicks on deselect button of the first of page elements located by css (&apos;.dropdown-selected-option&apos;) of input field where Text does include &quot;Second&quot;","startTime":"2026-01-05T21:11:23.878Z","children":[],"reportData":[],"screenshots":[{"screenshot":"photo-linux-webkit-26.0-tess-clicks-on-deselect-button-of-the-first-of-442f1deb81.png","screenshotName":"photo-linux-webkit-26.0-tess-clicks-on-deselect-button-of-the-first-of-442f1deb81.png","timeStamp":1767647484257},{"screenshot":"photo-linux-webkit-26.0-tess-clicks-on-deselect-button-of-the-first-of-442f1deb81.png","screenshotName":"photo-linux-webkit-26.0-tess-clicks-on-deselect-button-of-the-first-of-442f1deb81.png","timeStamp":1767647484105}],"duration":85,"result":"SUCCESS"},{"number":79,"description":"Tess ensures that the text of page elements located by css (&apos;.dropdown-selected-option&apos;) of input field does not contain &quot;Second&quot;","startTime":"2026-01-05T21:11:24.266Z","children":[],"reportData":[],"screenshots":[{"screenshot":"photo-linux-webkit-26.0-tess-ensures-that-the-text-of-page-elements-lo-442f1deb81.png","screenshotName":"photo-linux-webkit-26.0-tess-ensures-that-the-text-of-page-elements-lo-442f1deb81.png","timeStamp":1767647484410},{"screenshot":"photo-linux-webkit-26.0-tess-ensures-that-the-text-of-page-elements-lo-442f1deb81.png","screenshotName":"photo-linux-webkit-26.0-tess-ensures-that-the-text-of-page-elements-lo-442f1deb81.png","timeStamp":1767647484552}],"duration":4,"result":"SUCCESS"}],"reportData":[],"screenshots":[],"duration":684,"result":"SUCCESS"}],"reportData":[],"screenshots":[],"duration":1401,"result":"SUCCESS"}],"reportData":[],"screenshots":[],"duration":1412,"result":"SUCCESS"},{"number":80,"description":"Tess ensures that 0 does equal 0","startTime":"2026-01-05T21:11:24.596Z","children":[],"reportData":[],"screenshots":[{"screenshot":"photo-linux-webkit-26.0-tess-ensures-that-0-does-equal-0-442f1deb81.png","screenshotName":"photo-linux-webkit-26.0-tess-ensures-that-0-does-equal-0-442f1deb81.png","timeStamp":1767647484744},{"screenshot":"photo-linux-webkit-26.0-tess-ensures-that-0-does-equal-0-442f1deb81.png","screenshotName":"photo-linux-webkit-26.0-tess-ensures-that-0-does-equal-0-442f1deb81.png","timeStamp":1767647484882}],"duration":8,"result":"SUCCESS"},{"number":81,"description":"Tess ensures that placeholder of dropdown does equal &quot;Select option&quot;","startTime":"2026-01-05T21:11:24.888Z","children":[],"reportData":[],"screenshots":[{"screenshot":"photo-linux-webkit-26.0-tess-ensures-that-placeholder-of-dropdown-does-442f1deb81.png","screenshotName":"photo-linux-webkit-26.0-tess-ensures-that-placeholder-of-dropdown-does-442f1deb81.png","timeStamp":1767647485035},{"screenshot":"photo-linux-webkit-26.0-tess-ensures-that-placeholder-of-dropdown-does-442f1deb81.png","screenshotName":"photo-linux-webkit-26.0-tess-ensures-that-placeholder-of-dropdown-does-442f1deb81.png","timeStamp":1767647485174}],"duration":6,"result":"SUCCESS"}],"reportData":[],"screenshots":[],"duration":5896,"result":"SUCCESS"}],"userStory":{"id":"dropdown","storyName":"Dropdown","displayName":"Dropdown","path":"components/Dropdown/Dropdown","type":"feature","narrative":"","pathElements":[{"name":"components","description":"Components"},{"name":"Dropdown","description":"Dropdown"},{"name":"Dropdown","description":"Dropdown"}]},"dataTable":{"scenarioOutline":"","dataSetDescriptors":[{"name":"","description":"Max retries: 2","startRow":0,"rowCount":3}],"headers":["Retries"],"rows":[{"values":["Attempt #1"],"result":"SUCCESS"},{"values":["Attempt #1"],"result":"SUCCESS"},{"values":["Attempt #1"],"result":"SUCCESS"}],"predefinedRows":true},"startTime":"2026-01-05T21:10:28.654Z","testSource":"JS","tags":[{"name":"Components","type":"theme","displayName":"Components"},{"name":"Components/Dropdown","type":"capability","displayName":"Dropdown"},{"name":"Components/Dropdown/Dropdown","type":"feature","displayName":"Dropdown"},{"name":"chromium","type":"project","displayName":"chromium"},{"name":"Linux 6.11.0-1018-azure","type":"platform","platformName":"Linux","platformVersion":"6.11.0-1018-azure","displayName":"Linux 6.11.0-1018-azure"},{"name":"chromium 143.0.7499.4","type":"browser","browserName":"chromium","browserVersion":"143.0.7499.4","displayName":"chromium 143.0.7499.4"},{"name":"Components/Components","type":"theme","displayName":"Components"},{"name":"Components/Components/Dropdown/Dropdown","type":"feature","displayName":"Dropdown"},{"name":"firefox","type":"project","displayName":"firefox"},{"name":"firefox 144.0.2","type":"browser","browserName":"firefox","browserVersion":"144.0.2","displayName":"firefox 144.0.2"},{"name":"webkit","type":"project","displayName":"webkit"},{"name":"webkit 26.0","type":"browser","browserName":"webkit","browserVersion":"26.0","displayName":"webkit 26.0"}],"featureTag":{"name":"Components/Components/Dropdown/Dropdown","type":"feature","displayName":"Dropdown"},"context":"linux,chrome,firefox,safari","driver":"webkit","actors":[{"name":"Tess","can":["PerformActivities (PerformActivitiesAsPlaywrightSteps)","AnswerQuestions","RaiseErrors","ScheduleWork { scheduler: { clock: { timeAdjustment: { milliseconds: 0 } }, interactionTimeout: { milliseconds: 5000 } } }","BrowseTheWeb (BrowseTheWebWithPlaywright)","TakeNotes { notepad: {} }","CallAnApi { baseURL: \"http://localhost:3100\", headers: { common: { Accept: \"application/json, text/plain, */*\" } }, timeout: 10000 }"]}],"result":"SUCCESS","duration":56561}